{
    "sh": true,
    "x-terminal-emul": true,
    "kworker/u16:0": true,
    "systemd-journal": true,
    "node": true,
    "rcu_preempt": true,
    "rcu_sched": true,
    "test2": true,
    "irq/78-15200000": true,
    "roscore": true,
    "kworker/1:2": true,
    "test1": true,
    "in:imuxsock": true,
    "kworker/2:2": true,
    "tegradc.0/a": true,
    "rs:main Q:Reg": true,
    "sudo": true,
    "gmain": true,
    "bash": true,
    "irq/73-host_syn": true,
    "nvgpu_channel_p": true,
    "test4": true,
    "Xorg": true,
    "test3": true,
    "rosmaster": true,
    "rosout": true,
    "gdbus": true,
    "ibus-daemon": true,
    "ibus-engine-sim": true,
    "compiz": true,
    "kworker/u16:1": true,
    "irq/476-gk20a_s": true,
    "ksoftirqd/1": true,
    "kworker/4:4": true,
    "haveged": true,
    "roslaunch": true,
    "sugov:0": true,
    "kworker/7:2": true,
    "khugepaged": true,
    "kworker/6:1": true,
    "gsd-color": true,
    "python3": true,
    "jbd2/mmcblk0p1-": true,
    "mmc_cmdq_d/0": true,
    "kworker/6:1H": true,
    "kworker/0:1H": true,
    "containerd": true,
    "pool": true,
    "ssh-agent": true,
    "kworker/u17:1": true,
    "kthreadd": true,
    "nvgpu_pg_init_g": true,
    "kworker/5:1": true,
    "systemd-logind": true,
    "kworker/0:1": true,
    "systemd": true,
    "InputThread": true,
    "bamfdaemon": true,
    "ksoftirqd/0": true,
    "kworker/3:1": true,
    "update-notifier": true,
    "kworker/6:2": true,
    "kworker/4:1H": true,
    "watchdog/0": true,
    "sshd": true,
    "watchdog/1": true,
    "watchdog/2": true,
    "watchdog/3": true,
    "watchdog/4": true,
    "watchdog/5": true,
    "watchdog/6": true,
    "watchdog/7": true
}